etsm.py
etsm-0.5.0.dist-info/LICENSE
etsm-0.5.0.dist-info/METADATA
etsm-0.5.0.dist-info/WHEEL
etsm-0.5.0.dist-info/top_level.txt
etsm-0.5.0.dist-info/RECORD
