Metadata-Version: 2.1
Name: etsm
Version: 0.5.0
Summary: Efficient Tiny State Machine using object callbacks.
Home-page: UNKNOWN
Author: Eric Thiffeault
License: UNKNOWN
Platform: UNKNOWN
Classifier: Programming Language :: Python :: 3
Classifier: License :: OSI Approved :: MIT License
Classifier: Operating System :: OS Independent
Requires-Python: >=3.6
License-File: LICENSE
